dgp/VERSION
dgp/__init__.py
dgp/config/__init__.py
dgp/config/consts.py
dgp/config/log.py
dgp/core/__init__.py
dgp/core/base_dgp.py
dgp/core/base_enricher.py
dgp/core/config.py
dgp/core/config_validators.py
dgp/core/configurable_dgp.py
dgp/core/context.py
dgp/genera/__init__.py
dgp/genera/simple.py
dgp/genera/test_sample.py
dgp/genera/enrich/__init__.py
dgp/genera/enrich/enricher.py
dgp/genera/load/__init__.py
dgp/genera/load/loader.py
dgp/genera/load/analyzers/__init__.py
dgp/genera/load/analyzers/file_format/__init__.py
dgp/genera/load/analyzers/file_format/csv_format.py
dgp/genera/load/analyzers/file_format/file_format.py
dgp/genera/load/analyzers/file_format/file_format_dgp.py
dgp/genera/load/analyzers/file_format/gsheet_format.py
dgp/genera/load/analyzers/file_format/json_format.py
dgp/genera/load/analyzers/file_format/xls_format.py
dgp/genera/load/analyzers/structure/__init__.py
dgp/genera/load/analyzers/structure/header_fields.py
dgp/genera/load/analyzers/structure/skip_rows_cols.py
dgp/genera/load/analyzers/structure/structure_dgp.py
dgp/genera/publish/__init__.py
dgp/genera/publish/publisher.py
dgp/genera/transform/__init__.py
dgp/genera/transform/transform.py
dgp/genera/transform/analyzers/__init__.py
dgp/genera/transform/analyzers/mapping/__init__.py
dgp/genera/transform/analyzers/mapping/mandatory_fields.py
dgp/genera/transform/analyzers/mapping/map_guesser.py
dgp/genera/transform/analyzers/mapping/mapping_dgp.py
dgp/genera/transform/analyzers/mapping/primary_key.py
dgp/genera/transform/analyzers/taxonomies/__init__.py
dgp/genera/transform/analyzers/taxonomies/taxonomies_dgp.py
dgp/genera/transform/analyzers/taxonomies/taxonomy_fetcher.py
dgp/genera/transform/analyzers/taxonomies/taxonomy_guesser.py
dgp/genera/transform/analyzers/taxonomies/taxonomy_list.py
dgp/taxonomies/__init__.py
dgp/taxonomies/registry.py
dgp-0.1.3.dist-info/LICENSE
dgp-0.1.3.dist-info/METADATA
dgp-0.1.3.dist-info/WHEEL
dgp-0.1.3.dist-info/top_level.txt
dgp-0.1.3.dist-info/RECORD
