Metadata-Version: 2.1
Name: dgp
Version: 0.1.3
Summary: A data processing framework for data harmonisation
Home-page: https://github.com/dataspot/dgp
Author: Adam Kariv
Author-email: adam.kariv@gmail.com
License: MIT
Keywords: data
Platform: UNKNOWN
Classifier: Development Status :: 4 - Beta
Classifier: Intended Audience :: Developers
Classifier: License :: OSI Approved :: MIT License
Classifier: Operating System :: OS Independent
Classifier: Programming Language :: Python :: 3.6
Classifier: Programming Language :: Python :: 3.7
Classifier: Topic :: Software Development :: Libraries :: Python Modules
Requires-Dist: dataflows (>=0.3.20)
Requires-Dist: python-dateutil
Requires-Dist: PyYAML
Provides-Extra: develop
Requires-Dist: pylama ; extra == 'develop'
Requires-Dist: tox ; extra == 'develop'
